anobbsclient/__init__.py
anobbsclient/baseclient.py
anobbsclient/client.py
anobbsclient/exceptions.py
anobbsclient/objects.py
anobbsclient/options.py
anobbsclient/requestutils.py
anobbsclient/response.py
anobbsclient/usercookie.py
anobbsclient/utils.py
anobbsclient/walk/__init__.py
anobbsclient/walk/boardwalktarget.py
anobbsclient/walk/threadwalktarget.py
anobbsclient/walk/walk.py
anobbsclient/walk/walktarget.py
anobbsclient/walk/walkthread.py
anobbs_client-0.0.4.dist-info/LICENSE
anobbs_client-0.0.4.dist-info/METADATA
anobbs_client-0.0.4.dist-info/WHEEL
anobbs_client-0.0.4.dist-info/top_level.txt
anobbs_client-0.0.4.dist-info/RECORD
