Metadata-Version: 2.1
Name: anobbs-client
Version: 0.0.4
Summary: Simple AnoBBS API wrapper
Home-page: https://github.com/FToovvr/anobbs-client-py
Author: FToovvr
Author-email: FToovvr@protonmail.com
License: UNKNOWN
Platform: UNKNOWN
Classifier: Programming Language :: Python :: 3
Classifier: License :: OSI Approved :: MIT License
Classifier: Operating System :: OS Independent
Classifier: Development Status :: 2 - Pre-Alpha
Classifier: Natural Language :: Chinese (Simplified)
Requires-Python: >=3.8
Requires-Dist: python-dateutil (>=2.8.1)
Requires-Dist: requests (>=2.24)
Requires-Dist: requests-toolbelt (>=0.9.1)
